spark_fivetran_api/__init__.py
spark_fivetran_api/main_methods.py
spark_fivetran_api-0.1.1.dist-info/METADATA
spark_fivetran_api-0.1.1.dist-info/WHEEL
spark_fivetran_api-0.1.1.dist-info/top_level.txt
spark_fivetran_api-0.1.1.dist-info/RECORD
